envpicker/__init__.py
envpicker/logger.py
envpicker/manager/__init__.py
envpicker/manager/base.py
envpicker/manager/conda_mngr.py
envpicker/utils.py
envpicker-0.2.4.dist-info/LICENSE
envpicker-0.2.4.dist-info/METADATA
envpicker-0.2.4.dist-info/WHEEL
envpicker-0.2.4.dist-info/RECORD
